{
  "data": {
    "recipeId": 1,
    "name": "김치찌개",
    "kind": "찌개",
    "image": "",
    "inbun": "2인분",
    "level": "초보환영",
    "time": "30분이내",
    "materials": [
      {
        "materialId": 1,
        "name": "김치",
        "capacity": "300g",
        "type": "재료",
        "ingredientId": 1
      },
      {
        "materialId": 2,
        "name": "돼지고기",
        "capacity": "150g",
        "type": "재료",
        "ingredientId": 2
      },
      {
        "materialId": 3,
        "name": "두부",
        "capacity": "1모",
        "type": "재료",
        "ingredientId": 3
      },
      {
        "materialId": 4,
        "name": "양파",
        "capacity": "1/2개",
        "type": "재료",
        "ingredientId": 4
      },
      {
        "materialId": 5,
        "name": "대파",
        "capacity": "1대",
        "type": "재료",
        "ingredientId": 5
      },
      {
        "materialId": 6,
        "name": "청양고추",
        "capacity": "2개",
        "type": "재료",
        "ingredientId": 6
      },
      {
        "materialId": 7,
        "name": "다진 마늘",
        "capacity": "1큰술",
        "type": "재료",
        "ingredientId": 7
      },
      {
        "materialId": 8,
        "name": "참기름",
        "capacity": "1작은술",
        "type": "재료",
        "ingredientId": 8
      },
      {
        "materialId": 9,
        "name": "고추장",
        "capacity": "1큰술",
        "type": "재료",
        "ingredientId": 9
      },
      {
        "materialId": 10,
        "name": "물",
        "capacity": "2컵",
        "type": "재료",
        "ingredientId": 10
      }
    ],
    "steps": [
      {
        "stepId": 1,
        "content": "김치를 적당한 크기로 썰어주세요.",
        "image": ""
      },
      {
        "stepId": 2,
        "content": "돼지고기를 먼저 볶다가 김치를 넣고 함께 볶아주세요.",
        "image": ""
      }
    ]
  }
}
